publishing_boy/__init__.py
publishing_boy/cli.py
publishing_boy/plugins.py
publishing_boy/process.py
publishing_boy/publishing_boy.py
publishing_boy/template.py
publishing_boy/tests/__init__.py
publishing_boy/tests/test_register_plugins.py
publishing_boy/tests/utils.py
publishing_boy-0.1.5.dist-info/AUTHORS.rst
publishing_boy-0.1.5.dist-info/LICENSE
publishing_boy-0.1.5.dist-info/METADATA
publishing_boy-0.1.5.dist-info/WHEEL
publishing_boy-0.1.5.dist-info/entry_points.txt
publishing_boy-0.1.5.dist-info/top_level.txt
publishing_boy-0.1.5.dist-info/RECORD
