Metadata-Version: 2.1
Name: publishing-boy
Version: 0.1.5
Summary: Publishing Boy is preparing content for publishing
Home-page: https://github.com/przemekkot/publishing_boy
Author: Przemyslaw Kot
Author-email: przemyslaw.kot@gmail.com
License: MIT license
Keywords: publishing_boy
Platform: UNKNOWN
Classifier: Development Status :: 2 - Pre-Alpha
Classifier: Intended Audience :: Developers
Classifier: License :: OSI Approved :: MIT License
Classifier: Natural Language :: English
Classifier: Programming Language :: Python :: 2
Classifier: Programming Language :: Python :: 2.7
Classifier: Programming Language :: Python :: 3
Classifier: Programming Language :: Python :: 3.4
Classifier: Programming Language :: Python :: 3.5
Classifier: Programming Language :: Python :: 3.6
Classifier: Programming Language :: Python :: 3.7
Requires-Dist: Click (>=6.0)
Requires-Dist: Django (>=2.2.3)
